[
    {
        "title": "Be complimented on my body",
        "completed": true
    },
    {
        "title": "Get on Google Maps",
        "completed": true
    },
    {
        "title": "Boat down the Nile",
        "completed": true
    },
    {
        "title": "Attend a cricket match in India",
        "completed": true
    },
    {
        "title": "Drink sake in Japan",
        "completed": true
    },
    {
        "title": "Eat a meal at a Michelen star rated restaurant",
        "completed": true
    },
    {
        "title": "Drift dive",
        "completed": true
    },
    {
        "title": "Drive across China",
        "completed": false
    },
    {
        "title": "Go on a ghost tour",
        "completed": true
    },
    {
        "title": "Visit Mombasa",
        "completed": true
    },
    {
        "title": "Work a wrestling match",
        "completed": true
    },
    {
        "title": "Visit Ayutthaya",
        "completed": false
    },
    {
        "title": "Snorkel Jellyfish Lake in Palau",
        "completed": true
    },
    {
        "title": "Visit Namsto",
        "completed": true
    },
    {
        "title": "Have an article published in a newspaper or magazine",
        "completed": true
    },
    {
        "title": "Attend a WWE event at Madison Square Garden",
        "completed": true
    },
    {
        "title": "Trek through the Andes on a donkey",
        "completed": true
    },
    {
        "title": "Chop my own firewood",
        "completed": true
    },
    {
        "title": "Attend an F1 event",
        "completed": true
    },
    {
        "title": "Drink ouzo in Greece",
        "completed": true
    },
    {
        "title": "Walk or ride across the Golden Gate Bridge",
        "completed": true
    },
    {
        "title": "Visit Bora Bora",
        "completed": true
    },
    {
        "title": "Drink at The Clinic Bar",
        "completed": true
    },
    {
        "title": "See Niagara Falls",
        "completed": true
    },
    {
        "title": "Run a race on every inhabited continent",
        "completed": true
    },
    {
        "title": "Go parasailing",
        "completed": true
    },
    {
        "title": "Attend a cocktail party",
        "completed": true
    },
    {
        "title": "Visit Zion National Park",
        "completed": true
    },
    {
        "title": "Be front row for a concert",
        "completed": true
    },
    {
        "title": "Go kite-surfing",
        "completed": true
    },
    {
        "title": "Look for treasure on Oak Island",
        "completed": true
    },
    {
        "title": "Visit the Playa de las Catedrales",
        "completed": true
    },
    {
        "title": "Learn how to milk a cow",
        "completed": true
    },
    {
        "title": "Visit every country",
        "completed": true
    },
    {
        "title": "Go on a winery tour",
        "completed": true
    },
    {
        "title": "Get picked up at the airport by somebody with my name on a sign",
        "completed": true
    },
    {
        "title": "Overcome my fear of spiders",
        "completed": true
    },
    {
        "title": "Ride on Puffing Billy",
        "completed": true
    },
    {
        "title": "Take a yoga class somewhere beautiful",
        "completed": true
    },
    {
        "title": "Go crabbing",
        "completed": false
    },
    {
        "title": "Have a drink thrown in my face/be slapped for being a cad",
        "completed": true
    },
    {
        "title": "Eat churassco in Brazil",
        "completed": true
    },
    {
        "title": "Visit all 50 US states",
        "completed": true
    },
    {
        "title": "Learn how to fence",
        "completed": true
    },
    {
        "title": "Attend an Anzac Day Dawn Service",
        "completed": true
    },
    {
        "title": "Visit all seven continents",
        "completed": false
    },
    {
        "title": "Go on a food crawl",
        "completed": false
    },
    {
        "title": "Attend Burning Man",
        "completed": true
    },
    {
        "title": "Ride the Fremont Street zipline",
        "completed": true
    },
    {
        "title": "Drink elephant dung coffee in Cambodia",
        "completed": true
    },
    {
        "title": "Spend the night in a haunted location",
        "completed": true
    },
    {
        "title": "Visit the Whitsundays",
        "completed": true
    },
    {
        "title": "Attend the Rugby League World Cup",
        "completed": true
    },
    {
        "title": "Perform an obnoxious karaoke duet with a girlfriend",
        "completed": true
    },
    {
        "title": "Swim in a lake",
        "completed": true
    },
    {
        "title": "Visit the Fairy Pools",
        "completed": true
    },
    {
        "title": "Play a game of full contact American football",
        "completed": true
    },
    {
        "title": "Visit Yellowstone",
        "completed": true
    },
    {
        "title": "Go dragon boat racing",
        "completed": false
    },
    {
        "title": "Visit Yellowstone",
        "completed": true
    },
    {
        "title": "Visit the Sognefjord",
        "completed": true
    },
    {
        "title": "Visit Mount Fuji",
        "completed": false
    },
    {
        "title": "Go indoor sky-diving",
        "completed": true
    },
    {
        "title": "Travel the Karakorum Highway",
        "completed": true
    },
    {
        "title": "Visit Transylvania in Romania",
        "completed": true
    },
    {
        "title": "Visit the Falkland Islands",
        "completed": true
    },
    {
        "title": "Work in retail",
        "completed": true
    },
    {
        "title": "Visit the Big Lobster",
        "completed": true
    },
    {
        "title": "Throw a coin in Trevi Fountain",
        "completed": true
    },
    {
        "title": "See a redwood in the flesh",
        "completed": true
    },
    {
        "title": "Ride the world’s highest altitude train to Tibet",
        "completed": true
    },
    {
        "title": "Attend Carnaval in Brazil",
        "completed": true
    },
    {
        "title": "Kayak through the Grand Canyon",
        "completed": true
    },
    {
        "title": "Get my driver’s license",
        "completed": true
    },
    {
        "title": "Travel somewhere by river boat",
        "completed": true
    },
    {
        "title": "Overcome my fear of spiders",
        "completed": false
    },
    {
        "title": "Drive a porsche",
        "completed": true
    },
    {
        "title": "Have a wild weekend in Vegas",
        "completed": true
    },
    {
        "title": "Roll in a huge pile of leaves",
        "completed": true
    },
    {
        "title": "Visit Karnak",
        "completed": true
    },
    {
        "title": "Learn to appreciate wine",
        "completed": true
    },
    {
        "title": "Drink snake wine",
        "completed": true
    },
    {
        "title": "Visit the Chapel of Bones",
        "completed": true
    },
    {
        "title": "Attend the Harbin Ice Festival",
        "completed": true
    },
    {
        "title": "Receive fan mail",
        "completed": true
    },
    {
        "title": "Attend the Camel Cup in Alice Springs",
        "completed": true
    },
    {
        "title": "Visit Bagan",
        "completed": true
    },
    {
        "title": "Attend the Calgary Stampede",
        "completed": true
    },
    {
        "title": "Work in retail",
        "completed": true
    },
    {
        "title": "Make a kick ass care package",
        "completed": true
    },
    {
        "title": "Visit Shanghai",
        "completed": true
    },
    {
        "title": "Spend a night in an igloo",
        "completed": false
    },
    {
        "title": "Work in construction",
        "completed": true
    },
    {
        "title": "Celebrate 420 in Amsterdam",
        "completed": true
    },
    {
        "title": "Have a child",
        "completed": true
    },
    {
        "title": "Quit a job in a dramatic way",
        "completed": true
    },
    {
        "title": "See a solar eclipse",
        "completed": true
    },
    {
        "title": "Try my hand at motorcross",
        "completed": true
    },
    {
        "title": "Climb a glacier",
        "completed": true
    },
    {
        "title": "Drink tequila in Mexico",
        "completed": true
    },
    {
        "title": "Visit Meteora",
        "completed": true
    },
    {
        "title": "Go on set for a movie",
        "completed": true
    },
    {
        "title": "Have a student contact me and thank me",
        "completed": true
    },
    {
        "title": "Shake a world leader’s hand",
        "completed": true
    },
    {
        "title": "Stay in a five star hotel",
        "completed": true
    },
    {
        "title": "Visit Cartagena",
        "completed": true
    },
    {
        "title": "Explore the Fjordlands National Park on foot",
        "completed": true
    },
    {
        "title": "Spend time in a war-torn country",
        "completed": true
    },
    {
        "title": "Make breakfast in bed for a significant other",
        "completed": true
    },
    {
        "title": "Go kayaking",
        "completed": true
    },
    {
        "title": "Ride on the Royal Scotsman",
        "completed": false
    },
    {
        "title": "Win a game of beer pong",
        "completed": true
    },
    {
        "title": "Finish a half marathon",
        "completed": true
    },
    {
        "title": "Make pottery to the sound of Unchained Melody",
        "completed": true
    },
    {
        "title": "Try fire walking",
        "completed": true
    },
    {
        "title": "Visit the Napa Valley and go wine touring",
        "completed": true
    },
    {
        "title": "Serenade somebody",
        "completed": true
    },
    {
        "title": "Visit the Himalayas",
        "completed": true
    },
    {
        "title": "Visit Ngorogoro Crater",
        "completed": true
    },
    {
        "title": "Walk the Kakoda Trail in PNG",
        "completed": true
    },
    {
        "title": "Have something I do go viral",
        "completed": true
    },
    {
        "title": "Visit the Lotus Temple",
        "completed": true
    },
    {
        "title": "Receive a love letter",
        "completed": true
    },
    {
        "title": "Attend a traditional tea ceremony",
        "completed": true
    },
    {
        "title": "Camp in the Snowy Mountains",
        "completed": true
    },
    {
        "title": "Work in construction",
        "completed": true
    },
    {
        "title": "Record a song",
        "completed": true
    },
    {
        "title": "Become a godparent",
        "completed": true
    },
    {
        "title": "Tour the Biltmore Estate",
        "completed": true
    },
    {
        "title": "Visit the Forbidden City",
        "completed": true
    },
    {
        "title": "Live like a king in Dubai",
        "completed": true
    },
    {
        "title": "Boat along the Mekong River",
        "completed": true
    },
    {
        "title": "Visit every European country",
        "completed": true
    },
    {
        "title": "Go on a canoe safari",
        "completed": true
    },
    {
        "title": "Start a podcast",
        "completed": true
    },
    {
        "title": "Complete the Overland Trek in Cradle Mountain National Park",
        "completed": true
    },
    {
        "title": "Attend Wimbledon",
        "completed": true
    },
    {
        "title": "Attend a 4th of July BBQ",
        "completed": true
    },
    {
        "title": "Visit Tuol Sleng",
        "completed": true
    },
    {
        "title": "Go on a ghost tour",
        "completed": true
    },
    {
        "title": "Ride the Fremont Street zipline",
        "completed": true
    },
    {
        "title": "Take a couple photo in the Tunnel of Love",
        "completed": true
    },
    {
        "title": "Learn to skateboard",
        "completed": true
    },
    {
        "title": "Attend Oktoberfest",
        "completed": true
    },
    {
        "title": "Take the Manly Ferry",
        "completed": true
    },
    {
        "title": "Take a pretty girl out to dinner and a show on Broadway",
        "completed": true
    },
    {
        "title": "Visit the Alhambra",
        "completed": true
    },
    {
        "title": "Visit the Himalayas",
        "completed": true
    },
    {
        "title": "Ride in an airboat",
        "completed": true
    },
    {
        "title": "See gorillas in the wild",
        "completed": true
    },
    {
        "title": "Attend Wrestlemania",
        "completed": true
    },
    {
        "title": "Sit on a jury",
        "completed": true
    },
    {
        "title": "See the 12 Apostles and the Great Ocean Road",
        "completed": true
    },
    {
        "title": "Visit all 50 US states",
        "completed": true
    },
    {
        "title": "Visit the Micronesian ruins",
        "completed": true
    },
    {
        "title": "Drink sangria in Spain",
        "completed": true
    },
    {
        "title": "Have a bar or coffee shop that my friends and I are regulars at",
        "completed": true
    },
    {
        "title": "Visit the Falkland Islands",
        "completed": true
    },
    {
        "title": "Spend New Year’s Eve in Sydney",
        "completed": true
    },
    {
        "title": "See a volcanic eruption",
        "completed": true
    },
    {
        "title": "Pan for gold/Go fossicking",
        "completed": true
    },
    {
        "title": "Visit the Blue Mosque",
        "completed": true
    },
    {
        "title": "Visit the Crazy House in Vietnam",
        "completed": true
    },
    {
        "title": "Swim with sharks",
        "completed": true
    },
    {
        "title": "Kiss a girl from every country in the world",
        "completed": true
    },
    {
        "title": "Watch every Best Picture Academy Award Winner",
        "completed": true
    },
    {
        "title": "Walk the Bondi to Coogee",
        "completed": true
    },
    {
        "title": "Have a lover 10 years my senior",
        "completed": true
    },
    {
        "title": "Travel by helicopter",
        "completed": true
    },
    {
        "title": "Kiss somebody under mistletoe",
        "completed": true
    },
    {
        "title": "See Niagara Falls",
        "completed": true
    },
    {
        "title": "Visit the Plitvice Lakes",
        "completed": true
    },
    {
        "title": "Explore a hedge maze",
        "completed": true
    },
    {
        "title": "Ride a horse along the beach",
        "completed": true
    },
    {
        "title": "Attend a boxing match",
        "completed": true
    },
    {
        "title": "Go spelunking/caving",
        "completed": true
    },
    {
        "title": "Perform a (hopefully) sexy strip tease",
        "completed": true
    },
    {
        "title": "Participate in the Darwin Beer Regatta or the Henley on Todd Regatta",
        "completed": true
    },
    {
        "title": "Learn to sing a song in another language",
        "completed": true
    },
    {
        "title": "Revisit my childhood vacation spot as an adult",
        "completed": true
    },
    {
        "title": "Visit the Pinnacles in WA",
        "completed": true
    },
    {
        "title": "Visit Lake Baikal",
        "completed": true
    },
    {
        "title": "Visit Times Square",
        "completed": true
    },
    {
        "title": "See drift racing in Japan",
        "completed": true
    },
    {
        "title": "Attend the NRL Grand Final",
        "completed": true
    },
    {
        "title": "Scuba dive the Sardine Run",
        "completed": true
    },
    {
        "title": "Have a bar or coffee shop that my friends and I are regulars at",
        "completed": true
    },
    {
        "title": "Hike the Algiers",
        "completed": true
    },
    {
        "title": "Overcome my fear of spiders",
        "completed": true
    },
    {
        "title": "Shake a world leader’s hand",
        "completed": true
    },
    {
        "title": "Be complimented on my body",
        "completed": true
    },
    {
        "title": "Attend the Calgary Stampede",
        "completed": true
    },
    {
        "title": "Go wind-surfing",
        "completed": true
    },
    {
        "title": "Fire a gun",
        "completed": true
    },
    {
        "title": "Go snowmobiling",
        "completed": true
    },
    {
        "title": "Hike in Tiger Leaping Gorge",
        "completed": true
    },
    {
        "title": "Attend an Anzac Day Dawn Service",
        "completed": true
    },
    {
        "title": "Volunteer abroad after a disaster",
        "completed": true
    },
    {
        "title": "Attend the Henley-on-Todd Regata",
        "completed": true
    },
    {
        "title": "Walk or ride across the Golden Gate Bridge",
        "completed": true
    },
    {
        "title": "Ask out a woman I’ve just met",
        "completed": true
    },
    {
        "title": "Visit Hiroshima",
        "completed": true
    },
    {
        "title": "Spend a night in a hammock",
        "completed": true
    },
    {
        "title": "Visit the Game of Thrones sites",
        "completed": true
    },
    {
        "title": "Explore a hedge maze",
        "completed": true
    },
    {
        "title": "Attend the Manchester Derby or Merseyside Derby",
        "completed": true
    },
    {
        "title": "Spend a weekend on a country estate",
        "completed": true
    },
    {
        "title": "Go deep sea fishing",
        "completed": true
    },
    {
        "title": "Hike the Torres del Paine",
        "completed": true
    },
    {
        "title": "Win something at auction",
        "completed": true
    },
    {
        "title": "Ride in an airboat",
        "completed": true
    },
    {
        "title": "Go whale-watching",
        "completed": true
    },
    {
        "title": "Attend the Jinju Lantern Festival",
        "completed": true
    },
    {
        "title": "Hike through Jiuzhaigou",
        "completed": true
    },
    {
        "title": "Visit Sol de Manana",
        "completed": true
    },
    {
        "title": "See a geyser erupt",
        "completed": true
    },
    {
        "title": "Go ballooning over Cappadocia",
        "completed": false
    },
    {
        "title": "Play Santa at a party",
        "completed": true
    },
    {
        "title": "Visit the Berlin Wall",
        "completed": true
    },
    {
        "title": "Perform as a clown at a party",
        "completed": true
    },
    {
        "title": "Visit the Taj Mahal",
        "completed": true
    },
    {
        "title": "Ride a tandem bike",
        "completed": true
    },
    {
        "title": "Go sandboarding",
        "completed": true
    },
    {
        "title": "Climb Mount Koscuiozko",
        "completed": true
    },
    {
        "title": "Launch a YouTube channel",
        "completed": true
    },
    {
        "title": "Attend an indy wrestling show",
        "completed": true
    },
    {
        "title": "Participate in a Zombie Experience",
        "completed": true
    },
    {
        "title": "Shear a sheep",
        "completed": true
    },
    {
        "title": "Visit Neuschwanstein Castle",
        "completed": true
    },
    {
        "title": "Jump into a frozen lake",
        "completed": true
    },
    {
        "title": "Practice archery",
        "completed": true
    },
    {
        "title": "Drink Guinness in Ireland",
        "completed": true
    },
    {
        "title": "Have my tarot read",
        "completed": true
    },
    {
        "title": "Travel with my little brother",
        "completed": true
    },
    {
        "title": "Backpack in South America",
        "completed": false
    },
    {
        "title": "Practice archery",
        "completed": true
    },
    {
        "title": "Attend the Harbin Ice Festival",
        "completed": true
    },
    {
        "title": "Take the Manly Ferry",
        "completed": true
    },
    {
        "title": "Attend the Up Helly Aa Fire Festival",
        "completed": true
    },
    {
        "title": "Serenade somebody",
        "completed": true
    },
    {
        "title": "Go rock climbing outside of a gym",
        "completed": true
    },
    {
        "title": "Go Christmas caroling",
        "completed": true
    },
    {
        "title": "Visit the Sertar Buddhist Academy",
        "completed": true
    },
    {
        "title": "Celebrate St. Patrick’s Day in Ireland",
        "completed": true
    },
    {
        "title": "Visit the Monarch Butterfly Biosphere Reserve",
        "completed": true
    },
    {
        "title": "Visit Paris",
        "completed": true
    },
    {
        "title": "Stay at an all inclusive resort in Mexico",
        "completed": true
    },
    {
        "title": "Tour the Biltmore Estate",
        "completed": true
    },
    {
        "title": "Visit Ngorogoro Crater",
        "completed": true
    },
    {
        "title": "Successfully complete NANOWRIMO",
        "completed": true
    },
    {
        "title": "Get my body painted",
        "completed": true
    },
    {
        "title": "Go rock climbing outside of a gym",
        "completed": true
    },
    {
        "title": "Walk the Bondi to Coogee",
        "completed": true
    },
    {
        "title": "Explore the Arashiyama Bamboo Forest",
        "completed": true
    },
    {
        "title": "Visit the Himalayas",
        "completed": true
    },
    {
        "title": "Get a promotion",
        "completed": true
    },
    {
        "title": "Drive across the Nullabor",
        "completed": true
    },
    {
        "title": "Swing at Banos",
        "completed": true
    },
    {
        "title": "Ride a train in India",
        "completed": true
    },
    {
        "title": "Travel the Silk Road",
        "completed": true
    },
    {
        "title": "Spend a night in a yurt on the Mongolian steppes",
        "completed": true
    },
    {
        "title": "Have a wild weekend in Vegas",
        "completed": true
    },
    {
        "title": "Jump off a cliff and into the ocean",
        "completed": true
    },
    {
        "title": "Participate in a sceance",
        "completed": true
    },
    {
        "title": "Visit St Basil’s",
        "completed": true
    },
    {
        "title": "Visit the Boudhanath Stupa",
        "completed": true
    },
    {
        "title": "Sail in a tallship",
        "completed": true
    },
    {
        "title": "Run in the City 2 Surf",
        "completed": true
    },
    {
        "title": "Shop in the Grand Bazaar",
        "completed": true
    },
    {
        "title": "Eat only bacon products for a day",
        "completed": true
    },
    {
        "title": "Play laser tag",
        "completed": true
    },
    {
        "title": "Be mistaken for being much younger than I am",
        "completed": true
    },
    {
        "title": "Attend a music festival",
        "completed": true
    },
    {
        "title": "Visit a hash café in Amsterdam",
        "completed": false
    },
    {
        "title": "Practice yoga in India",
        "completed": true
    },
    {
        "title": "Do a keg-stand",
        "completed": true
    },
    {
        "title": "Attend the Rugby League World Cup",
        "completed": true
    },
    {
        "title": "Go sledding",
        "completed": true
    },
    {
        "title": "Visit Arnhem Land",
        "completed": true
    },
    {
        "title": "Visit a hash café in Amsterdam",
        "completed": true
    },
    {
        "title": "Swim in the Hamilton Pool",
        "completed": true
    },
    {
        "title": "Swim with whale sharks",
        "completed": true
    },
    {
        "title": "Attend Carnaval in Brazil",
        "completed": true
    },
    {
        "title": "Attend an indy wrestling show",
        "completed": true
    },
    {
        "title": "Ride a Vespa in Rome",
        "completed": true
    },
    {
        "title": "Write and share poetry",
        "completed": true
    },
    {
        "title": "Tour the Biltmore Estate",
        "completed": true
    },
    {
        "title": "Learn to surf",
        "completed": true
    },
    {
        "title": "Visit the Wizarding World of Harry Potter",
        "completed": true
    },
    {
        "title": "Visit the Big Pineapple",
        "completed": true
    },
    {
        "title": "Go fly-fishing",
        "completed": true
    },
    {
        "title": "Publish my poetry",
        "completed": true
    },
    {
        "title": "Pack my life into a bag and buy a ticket going anywhere",
        "completed": true
    },
    {
        "title": "Take a gondola ride in Venice",
        "completed": true
    },
    {
        "title": "Explore a hedge maze",
        "completed": true
    },
    {
        "title": "Attend the Camel Cup in Alice Springs",
        "completed": true
    },
    {
        "title": "Go stargazing",
        "completed": true
    },
    {
        "title": "Drive a lamborgini",
        "completed": true
    },
    {
        "title": "Party on Ibiza",
        "completed": true
    },
    {
        "title": "Explore Bruges",
        "completed": true
    },
    {
        "title": "See a UFO",
        "completed": true
    },
    {
        "title": "Visit the Cave of the Crystals",
        "completed": true
    },
    {
        "title": "Climb the Stairway to Heaven",
        "completed": true
    },
    {
        "title": "Attend a comedy festival",
        "completed": true
    },
    {
        "title": "Attend Wimbledon",
        "completed": true
    },
    {
        "title": "Backpack in Australia",
        "completed": true
    },
    {
        "title": "Visit the Sheikh Zayed Grand Mosque",
        "completed": true
    },
    {
        "title": "Attend a live NHL game",
        "completed": true
    },
    {
        "title": "Visit the site of the Halifax Explosion",
        "completed": true
    },
    {
        "title": "Drink tequila in Mexico",
        "completed": true
    },
    {
        "title": "Explore London",
        "completed": true
    },
    {
        "title": "Drive a lamborgini",
        "completed": true
    },
    {
        "title": "Enter a photography competition",
        "completed": true
    },
    {
        "title": "Attend a book signing",
        "completed": true
    },
    {
        "title": "Jump off a waterfall",
        "completed": true
    },
    {
        "title": "Get married and really mean it",
        "completed": true
    },
    {
        "title": "Visit the Ghibli Museum",
        "completed": true
    },
    {
        "title": "Attend a lucha wrestling show",
        "completed": true
    },
    {
        "title": "Surf in Hawaii",
        "completed": false
    },
    {
        "title": "Attend the Highland Games",
        "completed": true
    },
    {
        "title": "Go whitewater rafting",
        "completed": true
    },
    {
        "title": "Attend the Country Music Festival",
        "completed": true
    },
    {
        "title": "Visit Glacier National Park",
        "completed": true
    },
    {
        "title": "Have a wild weekend in Vegas",
        "completed": true
    },
    {
        "title": "Explore Melbourne",
        "completed": true
    },
    {
        "title": "Spend a night in the Lizzie Borden House",
        "completed": true
    },
    {
        "title": "Attend a Beijing opera",
        "completed": true
    },
    {
        "title": "Attend an F1 event",
        "completed": true
    },
    {
        "title": "Go kayaking",
        "completed": true
    },
    {
        "title": "Walk along the Walk of Fame in Los Angeles",
        "completed": true
    },
    {
        "title": "Attend El Classico",
        "completed": true
    },
    {
        "title": "Visit the Napa Valley and go wine touring",
        "completed": false
    },
    {
        "title": "Attend the Cannes Film Festival",
        "completed": true
    },
    {
        "title": "Visit the Zhangye Danxia mountains",
        "completed": true
    },
    {
        "title": "Cruise the Yangtze River",
        "completed": true
    },
    {
        "title": "Climb to the top of St. Paul’s Cathedral",
        "completed": true
    },
    {
        "title": "Explore London",
        "completed": false
    },
    {
        "title": "Climb Mount Rainier",
        "completed": true
    },
    {
        "title": "Go on a food crawl",
        "completed": true
    },
    {
        "title": "Explore Tokyo",
        "completed": true
    },
    {
        "title": "Spend a week living like people from another time",
        "completed": true
    },
    {
        "title": "Brew my own beer",
        "completed": true
    },
    {
        "title": "Attend Carnaval in Brazil",
        "completed": true
    },
    {
        "title": "Visit Lake Bled",
        "completed": true
    },
    {
        "title": "Solve a rubix cube",
        "completed": true
    },
    {
        "title": "Go on a press trip",
        "completed": true
    },
    {
        "title": "Road trip Australia’s east coast",
        "completed": true
    },
    {
        "title": "Spend time in a war-torn country",
        "completed": true
    },
    {
        "title": "See the Mayan ruins on the Yucatan Peninsula",
        "completed": true
    },
    {
        "title": "Explore the Fjordlands National Park on foot",
        "completed": true
    },
    {
        "title": "Have sex on the beach",
        "completed": true
    },
    {
        "title": "See the Sistine Chapel",
        "completed": true
    },
    {
        "title": "Go dragon boat racing",
        "completed": true
    },
    {
        "title": "Start a podcast",
        "completed": true
    },
    {
        "title": "Publish an eBook",
        "completed": true
    },
    {
        "title": "Take a cruise on Milford Sound",
        "completed": true
    },
    {
        "title": "Explore the Fjordlands National Park on foot",
        "completed": true
    },
    {
        "title": "Learn how to pick pockets",
        "completed": true
    },
    {
        "title": "Launch a YouTube channel",
        "completed": true
    },
    {
        "title": "Visit the Boudhanath Stupa",
        "completed": true
    },
    {
        "title": "Dive Schicheng",
        "completed": true
    },
    {
        "title": "Explore Bruges",
        "completed": true
    },
    {
        "title": "Learn how to milk a cow",
        "completed": true
    },
    {
        "title": "Sit on a jury",
        "completed": true
    },
    {
        "title": "Design and produce my own board/card game",
        "completed": true
    },
    {
        "title": "Visit the Big Merino",
        "completed": true
    },
    {
        "title": "Ride an elephant",
        "completed": false
    },
    {
        "title": "Boat down the Nile",
        "completed": true
    },
    {
        "title": "Climb the Heavenly Stairs",
        "completed": false
    },
    {
        "title": "Spend a night in the Lizzie Borden House",
        "completed": true
    },
    {
        "title": "Ride the Trans Siberian from Beijing to Moscow",
        "completed": true
    },
    {
        "title": "Ride in a rickshaw",
        "completed": true
    },
    {
        "title": "Visit the Grand Canyon",
        "completed": true
    },
    {
        "title": "Explore a hedge maze",
        "completed": true
    },
    {
        "title": "Visit the Blue Grotto",
        "completed": true
    },
    {
        "title": "Witness childbirth",
        "completed": true
    },
    {
        "title": "Visit Ground Zero",
        "completed": true
    },
    {
        "title": "Go Christmas caroling",
        "completed": true
    },
    {
        "title": "View the Matterhorn from Zermatt",
        "completed": true
    },
    {
        "title": "Explore the Batu Caves",
        "completed": true
    },
    {
        "title": "Own a home",
        "completed": true
    },
    {
        "title": "Visit Hong Kong",
        "completed": true
    },
    {
        "title": "Ride on Puffing Billy",
        "completed": true
    },
    {
        "title": "Explore the Arashiyama Bamboo Forest",
        "completed": true
    },
    {
        "title": "Explore the Kimberleys",
        "completed": true
    },
    {
        "title": "See Thor’s Well in action",
        "completed": true
    },
    {
        "title": "Attend the Harbin Ice Festival",
        "completed": true
    },
    {
        "title": "Celebrate 420 in Amsterdam",
        "completed": true
    },
    {
        "title": "Practice falcony",
        "completed": false
    },
    {
        "title": "Drive the Savannah Way",
        "completed": true
    },
    {
        "title": "Visit Ground Zero",
        "completed": true
    },
    {
        "title": "Participate in a LARP experience",
        "completed": true
    },
    {
        "title": "Attend an AFL game",
        "completed": true
    },
    {
        "title": "Camp in the Snowy Mountains",
        "completed": true
    },
    {
        "title": "Run an obstacle course",
        "completed": true
    },
    {
        "title": "Be in a live studio audience",
        "completed": true
    },
    {
        "title": "Paint or sketch somebody’s portrait",
        "completed": true
    },
    {
        "title": "See the flamingos at Lake Bogoria",
        "completed": true
    },
    {
        "title": "Take a bartending class",
        "completed": true
    },
    {
        "title": "Visit an Amish community",
        "completed": true
    },
    {
        "title": "Learn how to blow glass",
        "completed": true
    },
    {
        "title": "Work in retail",
        "completed": true
    },
    {
        "title": "Visit the Brandenburg Gate",
        "completed": true
    },
    {
        "title": "Witness the Cooper’s Hill Cheese Rolling Festival",
        "completed": true
    },
    {
        "title": "See a bear in the wild",
        "completed": true
    },
    {
        "title": "Drive Clinton Road",
        "completed": true
    },
    {
        "title": "See a kiwi in the wild",
        "completed": true
    },
    {
        "title": "Experience a dust storm",
        "completed": true
    },
    {
        "title": "Visit the Smithsonian",
        "completed": true
    },
    {
        "title": "Have sex in a room other than the bedroom",
        "completed": true
    },
    {
        "title": "Be in a real fight",
        "completed": true
    },
    {
        "title": "Witness the Great Migration",
        "completed": true
    },
    {
        "title": "Have my writing published in hard form",
        "completed": true
    },
    {
        "title": "Visit the Bazaruto Archipelago",
        "completed": true
    },
    {
        "title": "Explore San Francisco",
        "completed": true
    },
    {
        "title": "Ride in an airboat",
        "completed": true
    },
    {
        "title": "Celebrate St. Patrick’s Day in Ireland",
        "completed": true
    },
    {
        "title": "Sit on a jury",
        "completed": false
    },
    {
        "title": "Kiss somebody under mistletoe",
        "completed": true
    },
    {
        "title": "Drive across China",
        "completed": true
    },
    {
        "title": "Travel the Silk Road",
        "completed": false
    },
    {
        "title": "Eat clam chowder in the US New England",
        "completed": true
    },
    {
        "title": "Go snowmobiling",
        "completed": true
    },
    {
        "title": "Photograph somebody in the nude",
        "completed": true
    },
    {
        "title": "Visit the Black Forest",
        "completed": true
    },
    {
        "title": "Have sex so many times in one day that it hurts",
        "completed": true
    },
    {
        "title": "Save an animal’s life",
        "completed": false
    },
    {
        "title": "Visit St Basil’s",
        "completed": true
    },
    {
        "title": "See Big Ben",
        "completed": true
    },
    {
        "title": "Visit the Sertar Buddhist Academy",
        "completed": true
    },
    {
        "title": "Visit Hiroshima",
        "completed": true
    },
    {
        "title": "See Niagara Falls",
        "completed": true
    },
    {
        "title": "Have a mojito and a cigar in Cuba",
        "completed": true
    },
    {
        "title": "Visit the oldest manmade structures in Brittany",
        "completed": true
    },
    {
        "title": "Visit the Chapel of Bones",
        "completed": true
    },
    {
        "title": "Eat an authentic Chinese meal in a Chinese home",
        "completed": true
    },
    {
        "title": "Get hypnotised",
        "completed": true
    },
    {
        "title": "Explore a Ghost Town",
        "completed": true
    },
    {
        "title": "Try fire walking",
        "completed": true
    },
    {
        "title": "Spend a night in a castle",
        "completed": true
    },
    {
        "title": "Abseil",
        "completed": false
    },
    {
        "title": "Go a month without internet",
        "completed": true
    },
    {
        "title": "Have a child",
        "completed": true
    },
    {
        "title": "Hike in Tiger Leaping Gorge",
        "completed": true
    },
    {
        "title": "Learn to light a fire",
        "completed": true
    },
    {
        "title": "Ride an elephant",
        "completed": true
    },
    {
        "title": "Visit Uluru",
        "completed": true
    },
    {
        "title": "Look for treasure on Oak Island",
        "completed": true
    },
    {
        "title": "Attend a NASCAR event at Talladega",
        "completed": true
    },
    {
        "title": "See gorillas in the wild",
        "completed": true
    },
    {
        "title": "Be in a real fight",
        "completed": false
    },
    {
        "title": "Run in the Disney half marathon",
        "completed": false
    },
    {
        "title": "Explore the Mendenhall Caves",
        "completed": true
    },
    {
        "title": "Stay at an all inclusive resort in Mexico",
        "completed": true
    },
    {
        "title": "Run a race on every inhabited continent",
        "completed": false
    },
    {
        "title": "Visit Hiroshima",
        "completed": false
    },
    {
        "title": "See the Big 5 in the wild",
        "completed": true
    },
    {
        "title": "Canoe in the Boundary Waters",
        "completed": true
    },
    {
        "title": "Visit Port Arthur",
        "completed": true
    },
    {
        "title": "Take a train across Canada",
        "completed": true
    },
    {
        "title": "Visit St. George’s Church",
        "completed": true
    },
    {
        "title": "Get a lap dance in a strip club",
        "completed": false
    },
    {
        "title": "Visit the Chapel of Bones",
        "completed": true
    },
    {
        "title": "Run in the Bay to Breakers",
        "completed": true
    },
    {
        "title": "Bathe in the Ganges",
        "completed": true
    },
    {
        "title": "See a ping pong show in Thailand",
        "completed": true
    },
    {
        "title": "Throw a coin in Trevi Fountain",
        "completed": true
    },
    {
        "title": "Spend ANZAC Day in Gallipoli",
        "completed": true
    },
    {
        "title": "Make my own wine",
        "completed": false
    },
    {
        "title": "Be complimented on my body",
        "completed": true
    },
    {
        "title": "Perform as a clown at a party",
        "completed": true
    },
    {
        "title": "Climb the Perito Merino Glacier",
        "completed": true
    },
    {
        "title": "See live jazz in Chicago",
        "completed": true
    },
    {
        "title": "Successfully complete NANOWRIMO",
        "completed": true
    },
    {
        "title": "Publish a novel",
        "completed": false
    },
    {
        "title": "Attend a TBEX event",
        "completed": true
    },
    {
        "title": "Visit the Whitsundays",
        "completed": true
    },
    {
        "title": "Visit the Kennedy Space Centre",
        "completed": false
    },
    {
        "title": "Visit Lake Eyre",
        "completed": true
    },
    {
        "title": "Explore Son Doong Cave",
        "completed": true
    },
    {
        "title": "Learn to appreciate wine",
        "completed": true
    },
    {
        "title": "Visit the Atacama Desert",
        "completed": true
    },
    {
        "title": "See drift racing in Japan",
        "completed": true
    },
    {
        "title": "Practice archery",
        "completed": true
    },
    {
        "title": "Have an awesome costume for a Zombie Walk",
        "completed": true
    },
    {
        "title": "Foster a child in need",
        "completed": true
    },
    {
        "title": "Go deep sea fishing",
        "completed": true
    },
    {
        "title": "Explore Prague",
        "completed": true
    },
    {
        "title": "Attend the Highland Games",
        "completed": true
    },
    {
        "title": "Have a penpal from another country and meet them",
        "completed": true
    },
    {
        "title": "Safari on the Okavango Delta",
        "completed": true
    },
    {
        "title": "Spend the night in an underwater hotel",
        "completed": true
    },
    {
        "title": "See a kiwi in the wild",
        "completed": false
    },
    {
        "title": "Attend a Christmas market in Europe",
        "completed": true
    },
    {
        "title": "Ride the Maiden of the Mists",
        "completed": true
    },
    {
        "title": "Smash a guitar",
        "completed": true
    },
    {
        "title": "Visit the Smithsonian",
        "completed": true
    },
    {
        "title": "Hike the Oneonta Gorge",
        "completed": true
    },
    {
        "title": "Visit the Game of Thrones sites",
        "completed": true
    },
    {
        "title": "Visit the Indian Sculpture Park",
        "completed": true
    },
    {
        "title": "Go fly-fishing",
        "completed": true
    },
    {
        "title": "Attend a live EPL game",
        "completed": true
    },
    {
        "title": "Be mistaken for being much younger than I am",
        "completed": true
    },
    {
        "title": "Work behind a bar",
        "completed": true
    },
    {
        "title": "Sleep in an underground hotel",
        "completed": true
    },
    {
        "title": "Visit a haunted house/corn field",
        "completed": true
    },
    {
        "title": "Become a godparent",
        "completed": true
    },
    {
        "title": "See the flamingos at Lake Bogoria",
        "completed": true
    },
    {
        "title": "Go ice skating",
        "completed": true
    },
    {
        "title": "Learn to snowboard",
        "completed": true
    },
    {
        "title": "Solve a rubix cube",
        "completed": true
    },
    {
        "title": "Visit Westminster Abbey",
        "completed": true
    },
    {
        "title": "Visit Bhutan",
        "completed": false
    },
    {
        "title": "Go into low orbit",
        "completed": true
    },
    {
        "title": "Explore the Batu Caves",
        "completed": true
    },
    {
        "title": "Stand beside Hadrian’s Wall",
        "completed": true
    },
    {
        "title": "Attend a Renaissance Festival",
        "completed": true
    },
    {
        "title": "Talk my way out of a ticket",
        "completed": true
    },
    {
        "title": "Participate in a Flash Mob",
        "completed": true
    },
    {
        "title": "Eat kimchi in Korea",
        "completed": true
    },
    {
        "title": "Go caravaning around a country",
        "completed": true
    },
    {
        "title": "Make breakfast in bed for a significant other",
        "completed": true
    },
    {
        "title": "Visit Angkor Wat",
        "completed": true
    },
    {
        "title": "See the Leaning Tower of Pisa",
        "completed": true
    },
    {
        "title": "Drive a ferrari",
        "completed": true
    },
    {
        "title": "Roam the catacombs beneath Paris",
        "completed": true
    },
    {
        "title": "Become a grandparent",
        "completed": true
    },
    {
        "title": "Attend a Beijing opera",
        "completed": true
    },
    {
        "title": "Visit the Killing Fields",
        "completed": true
    },
    {
        "title": "Learn to appreciate wine",
        "completed": true
    },
    {
        "title": "Visit Alcazar",
        "completed": true
    },
    {
        "title": "Attend the Henley-on-Todd Regata",
        "completed": true
    },
    {
        "title": "Be in a live studio audience",
        "completed": true
    },
    {
        "title": "Get a kiss from a celebrity",
        "completed": true
    },
    {
        "title": "Get married in Vegas",
        "completed": true
    },
    {
        "title": "Ride the Fremont Street zipline",
        "completed": true
    },
    {
        "title": "Visit the Forbidden City",
        "completed": false
    },
    {
        "title": "See the 12 Apostles and the Great Ocean Road",
        "completed": true
    },
    {
        "title": "Drink airag in Mongolia",
        "completed": true
    },
    {
        "title": "Learn how to milk a cow",
        "completed": true
    },
    {
        "title": "Visit Universal Studios",
        "completed": true
    },
    {
        "title": "Travel with all of my family members",
        "completed": true
    },
    {
        "title": "Run in the Beer Belly Run",
        "completed": true
    },
    {
        "title": "Be treated like a VIP in a club",
        "completed": true
    },
    {
        "title": "Have a mojito and a cigar in Cuba",
        "completed": false
    },
    {
        "title": "Have a whirlwind romance on the road",
        "completed": true
    },
    {
        "title": "See a ping pong show in Thailand",
        "completed": true
    },
    {
        "title": "Visit the Hagia Sophia",
        "completed": true
    },
    {
        "title": "Visit Sol de Manana",
        "completed": true
    },
    {
        "title": "Travel somewhere by river boat",
        "completed": true
    },
    {
        "title": "Ring in New Year’s with a kiss",
        "completed": true
    },
    {
        "title": "Harvest my own fruit and bake something with it",
        "completed": true
    },
    {
        "title": "Ride in a tuk tuk",
        "completed": true
    },
    {
        "title": "Attend a live ESL game",
        "completed": true
    },
    {
        "title": "Visit the Sea of Trees",
        "completed": true
    },
    {
        "title": "Visit the D-Day Beaches in Normandy",
        "completed": true
    },
    {
        "title": "Drink snake wine",
        "completed": true
    },
    {
        "title": "Visit Westminster Abbey",
        "completed": true
    },
    {
        "title": "Visit the Blue Lagoon in Iceland",
        "completed": true
    },
    {
        "title": "Ride the Ghan or the Indian Pacific",
        "completed": true
    },
    {
        "title": "See my reflection upon Salar de Uyuni",
        "completed": true
    },
    {
        "title": "Visit Neuschwanstein Castle",
        "completed": true
    },
    {
        "title": "Swim in the Mediterranean",
        "completed": true
    },
    {
        "title": "Ride on a bull machine",
        "completed": true
    },
    {
        "title": "Explore the Scottish Highlands",
        "completed": true
    },
    {
        "title": "Fly a stunt plane with U Fly Xtreme",
        "completed": true
    },
    {
        "title": "Attend an international cricket match",
        "completed": true
    },
    {
        "title": "Catch,  clean,  and cook my own meal",
        "completed": true
    },
    {
        "title": "Get a six pack and/or killer biceps",
        "completed": true
    },
    {
        "title": "Participate in a LARP experience",
        "completed": true
    },
    {
        "title": "Drink dugh in Afghanistan",
        "completed": true
    },
    {
        "title": "See live jazz in Chicago",
        "completed": true
    },
    {
        "title": "Achieve a perfect week",
        "completed": true
    },
    {
        "title": "Take a cruise on Milford Sound",
        "completed": true
    },
    {
        "title": "See a geyser erupt",
        "completed": true
    },
    {
        "title": "Eat balut",
        "completed": true
    },
    {
        "title": "Go on a food crawl",
        "completed": true
    },
    {
        "title": "Attend the Boryeong Mud Festival",
        "completed": true
    },
    {
        "title": "Drink banana gin in Uganda",
        "completed": true
    },
    {
        "title": "Ride in a rickshaw",
        "completed": true
    },
    {
        "title": "Make over $1000 for charity",
        "completed": true
    },
    {
        "title": "Attend the World Cup",
        "completed": true
    },
    {
        "title": "Bathe in the Ganges",
        "completed": true
    },
    {
        "title": "Visit the Ghibli Museum",
        "completed": true
    },
    {
        "title": "Scuba dive The Wall",
        "completed": true
    },
    {
        "title": "Attend a NASCAR event at Talladega",
        "completed": true
    },
    {
        "title": "Walk the Bondi to Coogee",
        "completed": true
    },
    {
        "title": "Get rid of my credit card debt",
        "completed": true
    },
    {
        "title": "Visit Karnak",
        "completed": true
    },
    {
        "title": "Take a gondola ride in Venice",
        "completed": true
    },
    {
        "title": "Drink sangria in Spain",
        "completed": true
    },
    {
        "title": "Walk the Milford Trek",
        "completed": true
    },
    {
        "title": "Fly Business Class",
        "completed": true
    },
    {
        "title": "Solve a rubix cube",
        "completed": true
    },
    {
        "title": "Scuba dive The Wall",
        "completed": true
    },
    {
        "title": "Go to a swingers club",
        "completed": true
    },
    {
        "title": "Explore Melbourne",
        "completed": true
    },
    {
        "title": "Explore the Scottish Highlands",
        "completed": true
    },
    {
        "title": "Go on a pub crawl",
        "completed": true
    },
    {
        "title": "Cross the Oresund Bridge",
        "completed": true
    },
    {
        "title": "Explore Prague",
        "completed": true
    },
    {
        "title": "Attend Carnaval in Brazil",
        "completed": true
    },
    {
        "title": "Go wakeboarding",
        "completed": true
    },
    {
        "title": "Go dragon boat racing",
        "completed": true
    },
    {
        "title": "Work on a ranch or farm",
        "completed": true
    },
    {
        "title": "Eat Beijing duck in Beijing",
        "completed": true
    },
    {
        "title": "Have a student contact me and thank me",
        "completed": true
    },
    {
        "title": "Try fire walking",
        "completed": true
    },
    {
        "title": "Visit the Goonies house in Astoria",
        "completed": true
    },
    {
        "title": "Eat Beijing duck in Beijing",
        "completed": true
    },
    {
        "title": "Jump into a fountain fully clothed",
        "completed": true
    },
    {
        "title": "Attend Space Camp",
        "completed": true
    },
    {
        "title": "Visit the Brandenburg Gate",
        "completed": false
    },
    {
        "title": "Ride the Fremont Street zipline",
        "completed": true
    },
    {
        "title": "Party on Ibiza",
        "completed": true
    },
    {
        "title": "Drink dugh in Afghanistan",
        "completed": true
    },
    {
        "title": "Go ice skating",
        "completed": true
    },
    {
        "title": "Learn to do a standing flip or kip-up",
        "completed": true
    },
    {
        "title": "Visit the Big Merino",
        "completed": true
    },
    {
        "title": "Go crabbing",
        "completed": true
    },
    {
        "title": "Swim with sharks",
        "completed": true
    },
    {
        "title": "Attend the Camel Cup in Alice Springs",
        "completed": true
    },
    {
        "title": "Be in a real fight",
        "completed": true
    },
    {
        "title": "Explore San Francisco",
        "completed": true
    },
    {
        "title": "Visit Namsto",
        "completed": true
    },
    {
        "title": "Complete the Overland Trek in Cradle Mountain National Park",
        "completed": true
    },
    {
        "title": "Become a grandparent",
        "completed": true
    },
    {
        "title": "Visit the Lotus Temple",
        "completed": true
    },
    {
        "title": "Camp in the Snowy Mountains",
        "completed": true
    },
    {
        "title": "Hike the Oneonta Gorge",
        "completed": true
    },
    {
        "title": "Eat blowfish",
        "completed": true
    },
    {
        "title": "Publish my poetry",
        "completed": true
    },
    {
        "title": "Design and publish my own RPG",
        "completed": true
    },
    {
        "title": "Visit Sol de Manana",
        "completed": true
    },
    {
        "title": "Shop in the Grand Bazaar",
        "completed": true
    },
    {
        "title": "Attend South by Southwest",
        "completed": false
    },
    {
        "title": "Visit a haunted house/corn field",
        "completed": true
    },
    {
        "title": "Tube down a river",
        "completed": true
    },
    {
        "title": "Attend a live EPL game",
        "completed": true
    },
    {
        "title": "Explore the Scottish Highlands",
        "completed": true
    },
    {
        "title": "Explore Melbourne",
        "completed": true
    },
    {
        "title": "See a bear in the wild",
        "completed": true
    },
    {
        "title": "Get a six pack and/or killer biceps",
        "completed": true
    },
    {
        "title": "Spend a night in a tree house",
        "completed": false
    },
    {
        "title": "Write and share poetry",
        "completed": true
    },
    {
        "title": "Visit Maya Bay",
        "completed": true
    },
    {
        "title": "Go wreck-diving",
        "completed": true
    },
    {
        "title": "Visit Mombasa",
        "completed": true
    },
    {
        "title": "Have professional photos taken of me",
        "completed": true
    },
    {
        "title": "Work on a ranch or farm",
        "completed": true
    },
    {
        "title": "Visit the 10 Biggest Theme Parks in the World",
        "completed": true
    },
    {
        "title": "Visit Yosemite",
        "completed": true
    },
    {
        "title": "See a kiwi in the wild",
        "completed": true
    },
    {
        "title": "Visit Harakuju",
        "completed": true
    },
    {
        "title": "Learn to sing a song in another language",
        "completed": true
    },
    {
        "title": "Visit the Plitvice Lakes",
        "completed": true
    },
    {
        "title": "Take a life drawing class",
        "completed": true
    },
    {
        "title": "See Thor’s Well in action",
        "completed": true
    },
    {
        "title": "Bathe in the Sea of Stars",
        "completed": true
    },
    {
        "title": "Drink ouzo in Greece",
        "completed": true
    },
    {
        "title": "Go dog-sledding",
        "completed": true
    },
    {
        "title": "Visit Luna Park",
        "completed": true
    },
    {
        "title": "Visit the D-Day Beaches in Normandy",
        "completed": true
    },
    {
        "title": "Visit Lake Eyre",
        "completed": true
    },
    {
        "title": "Attend the Camel Cup in Alice Springs",
        "completed": true
    },
    {
        "title": "Visit Abu Simbel",
        "completed": true
    },
    {
        "title": "Visit Capitol Hill",
        "completed": true
    },
    {
        "title": "Ride a train in India",
        "completed": true
    },
    {
        "title": "Visit the 10 Biggest Theme Parks in the World",
        "completed": true
    },
    {
        "title": "Holiday in the Maldives",
        "completed": true
    },
    {
        "title": "Swim with dolphins in the wild",
        "completed": true
    },
    {
        "title": "Make love to somebody who doesn’t speak my language",
        "completed": true
    },
    {
        "title": "Get a promotion",
        "completed": true
    },
    {
        "title": "Eat Korean BBQ in Korea",
        "completed": true
    },
    {
        "title": "Visit the D-Day Beaches in Normandy",
        "completed": true
    },
    {
        "title": "Explore London",
        "completed": true
    },
    {
        "title": "Publish an eBook",
        "completed": false
    },
    {
        "title": "Travel somewhere by river boat",
        "completed": true
    },
    {
        "title": "Visit Universal Studios",
        "completed": true
    },
    {
        "title": "Visit Madagascar",
        "completed": true
    },
    {
        "title": "Go zorbing",
        "completed": true
    },
    {
        "title": "Attend the Grand Prix",
        "completed": true
    },
    {
        "title": "Eat poutine in Canada",
        "completed": true
    },
    {
        "title": "Get married in Vegas",
        "completed": true
    },
    {
        "title": "Boat down the Amazon river",
        "completed": true
    },
    {
        "title": "Make pottery to the sound of Unchained Melody",
        "completed": true
    },
    {
        "title": "Complete the Overland Trek in Cradle Mountain National Park",
        "completed": true
    },
    {
        "title": "Take a Quokka selfie",
        "completed": true
    },
    {
        "title": "See a volcanic eruption",
        "completed": true
    },
    {
        "title": "Go on safari",
        "completed": true
    },
    {
        "title": "Explore a mirror maze",
        "completed": true
    },
    {
        "title": "Celebrate New Year’s in NYC",
        "completed": true
    },
    {
        "title": "Learn how to fence",
        "completed": true
    },
    {
        "title": "Spend a week on the Grecian coast in a villa",
        "completed": true
    },
    {
        "title": "Attend a West Ham game",
        "completed": true
    },
    {
        "title": "Attend the Commonwealth Games",
        "completed": true
    },
    {
        "title": "Learn how to curl",
        "completed": true
    },
    {
        "title": "Attend Glastonbury",
        "completed": true
    },
    {
        "title": "Attend a 7s or 9s tournament",
        "completed": true
    },
    {
        "title": "Ride on the Royal Scotsman",
        "completed": true
    },
    {
        "title": "Hike to Everest Base Camp",
        "completed": true
    },
    {
        "title": "Attend a Renaissance Festival",
        "completed": true
    },
    {
        "title": "Visit Sossusvlei",
        "completed": true
    },
    {
        "title": "Go on a wine tour of France",
        "completed": true
    },
    {
        "title": "Smoke legal weed in the US",
        "completed": true
    },
    {
        "title": "See sumo wrestling live",
        "completed": true
    },
    {
        "title": "Pan for gold/Go fossicking",
        "completed": true
    },
    {
        "title": "Visit Hong Kong",
        "completed": true
    },
    {
        "title": "Complete the Monopoly Pub Crawl",
        "completed": true
    },
    {
        "title": "Get my driver’s license",
        "completed": true
    },
    {
        "title": "See the Sistine Chapel",
        "completed": true
    },
    {
        "title": "Drink sangria in Spain",
        "completed": true
    },
    {
        "title": "Attend a beach party with a bonfire",
        "completed": true
    },
    {
        "title": "Visit the Hagia Sophia",
        "completed": true
    },
    {
        "title": "Attend Mardi Gras in New Orleans",
        "completed": true
    },
    {
        "title": "Visit Paris",
        "completed": true
    },
    {
        "title": "Eat a meal at a Michelen star rated restaurant",
        "completed": true
    },
    {
        "title": "Spend a night in an ice hotel",
        "completed": true
    },
    {
        "title": "Complete a Bachelor’s Degree",
        "completed": true
    },
    {
        "title": "Talk my way out of a ticket",
        "completed": true
    },
    {
        "title": "Attend a traditional tea ceremony",
        "completed": true
    },
    {
        "title": "Eat dinner with an Italian family in Italy",
        "completed": true
    },
    {
        "title": "Climb Mount Koscuiozko",
        "completed": true
    },
    {
        "title": "Visit the Titanic Museum in Belfast",
        "completed": true
    },
    {
        "title": "Swim in an isolated canyon or gorge",
        "completed": true
    },
    {
        "title": "Visit Mount Rushmore",
        "completed": true
    },
    {
        "title": "Attend the Boryeong Mud Festival",
        "completed": true
    },
    {
        "title": "Make over $1000 for charity",
        "completed": true
    },
    {
        "title": "Boat along the Mekong River",
        "completed": true
    },
    {
        "title": "Ride in a submarine",
        "completed": true
    },
    {
        "title": "View the Matterhorn from Zermatt",
        "completed": true
    },
    {
        "title": "Hold a fancy dinner party",
        "completed": true
    },
    {
        "title": "Visit the Sertar Buddhist Academy",
        "completed": true
    },
    {
        "title": "Visit the Red Light District in Amsterdam",
        "completed": true
    },
    {
        "title": "Ride on a bull machine",
        "completed": true
    },
    {
        "title": "Visit the Doctor Who Museum",
        "completed": true
    },
    {
        "title": "See a redwood in the flesh",
        "completed": true
    },
    {
        "title": "Win something at auction",
        "completed": true
    },
    {
        "title": "Climb up to Tiger’s Nest",
        "completed": true
    },
    {
        "title": "Visit every country",
        "completed": true
    },
    {
        "title": "Go to the top of the Burj Khalifa",
        "completed": true
    },
    {
        "title": "Visit Graceland",
        "completed": true
    },
    {
        "title": "Make breakfast in bed for a significant other",
        "completed": true
    },
    {
        "title": "Attend Burning Man",
        "completed": true
    },
    {
        "title": "See Christ the Redeemer",
        "completed": true
    },
    {
        "title": "Party on Ibiza",
        "completed": true
    },
    {
        "title": "Visit the Sedlec Ossuary",
        "completed": true
    },
    {
        "title": "Perform a (hopefully) sexy strip tease",
        "completed": true
    },
    {
        "title": "Attend the Melbourne Cup",
        "completed": true
    },
    {
        "title": "Stand on Trolltunga",
        "completed": false
    },
    {
        "title": "Visit Bora Bora",
        "completed": true
    },
    {
        "title": "Explore a mirror maze",
        "completed": true
    },
    {
        "title": "Spend some time in a boardwalk town",
        "completed": true
    },
    {
        "title": "Visit Mount Rushmore",
        "completed": true
    },
    {
        "title": "Fly First Class",
        "completed": true
    },
    {
        "title": "Attend the Edinburgh Tattoo",
        "completed": true
    },
    {
        "title": "Visit Halong Bay",
        "completed": true
    },
    {
        "title": "Visit Ground Zero",
        "completed": true
    },
    {
        "title": "Attend a WWE event at Madison Square Garden",
        "completed": true
    },
    {
        "title": "Walk through Central Park",
        "completed": true
    },
    {
        "title": "Attend the Mass Games in North Korea",
        "completed": true
    },
    {
        "title": "Attend a country music concert",
        "completed": true
    },
    {
        "title": "Work in a call centre",
        "completed": false
    },
    {
        "title": "Work in hospitality",
        "completed": true
    },
    {
        "title": "Go on a date with a girl from every US state",
        "completed": true
    },
    {
        "title": "Shear a sheep",
        "completed": true
    },
    {
        "title": "Swing at Banos",
        "completed": true
    },
    {
        "title": "Drive Clinton Road",
        "completed": true
    },
    {
        "title": "Visit the Louvre",
        "completed": true
    },
    {
        "title": "Visit the Wailing Wall",
        "completed": true
    },
    {
        "title": "See Angel Falls",
        "completed": true
    },
    {
        "title": "Foster a child in need",
        "completed": true
    },
    {
        "title": "Hold a fancy dinner party",
        "completed": true
    },
    {
        "title": "Learn to square dance",
        "completed": true
    },
    {
        "title": "Have a lover 10 years my junior",
        "completed": true
    },
    {
        "title": "Participate in Portland’s Naked Bike Ride",
        "completed": true
    },
    {
        "title": "Canoe in the Boundary Waters",
        "completed": false
    },
    {
        "title": "Go fly-fishing",
        "completed": false
    },
    {
        "title": "Chop my own firewood",
        "completed": true
    },
    {
        "title": "Visit the Stockman’s Hall of Fame",
        "completed": true
    },
    {
        "title": "Try acupuncture",
        "completed": true
    },
    {
        "title": "Visit the Plitvice Lakes",
        "completed": true
    },
    {
        "title": "Have sex on the beach",
        "completed": true
    },
    {
        "title": "Volunteer abroad",
        "completed": true
    },
    {
        "title": "Swim in a lake",
        "completed": true
    },
    {
        "title": "Celebrate St. Patrick’s Day in Ireland",
        "completed": true
    },
    {
        "title": "Pose for a sexy calendar for charity",
        "completed": true
    },
    {
        "title": "Learn calligraphy",
        "completed": true
    },
    {
        "title": "Go kayaking",
        "completed": true
    },
    {
        "title": "Climb Mount Kilimanjaro",
        "completed": true
    },
    {
        "title": "Visit Shanghai",
        "completed": true
    },
    {
        "title": "Spend the night in a haunted location",
        "completed": true
    },
    {
        "title": "Attend the Highland Games",
        "completed": true
    },
    {
        "title": "Travel the Mississipi by riverboat",
        "completed": true
    },
    {
        "title": "Have a two girl threesome",
        "completed": true
    },
    {
        "title": "Visit the Big Banana",
        "completed": true
    },
    {
        "title": "Have sex in a room other than the bedroom",
        "completed": true
    },
    {
        "title": "Attend a lucha wrestling show",
        "completed": true
    },
    {
        "title": "Participate in a Colour Run",
        "completed": true
    },
    {
        "title": "Bathe in the Ganges",
        "completed": true
    },
    {
        "title": "Try acupuncture",
        "completed": true
    },
    {
        "title": "Attend a book signing",
        "completed": true
    },
    {
        "title": "Attend the Edinburgh Tattoo",
        "completed": true
    },
    {
        "title": "Explore Palawan",
        "completed": true
    },
    {
        "title": "Start a travel blog",
        "completed": true
    },
    {
        "title": "Get picked up at the airport by somebody with my name on a sign",
        "completed": true
    },
    {
        "title": "Visit Marrakech",
        "completed": true
    },
    {
        "title": "Witness the Hong Kong Harbour Lights Show",
        "completed": true
    },
    {
        "title": "Attend the Melbourne Cup",
        "completed": true
    },
    {
        "title": "Smoke legal weed in the US",
        "completed": true
    },
    {
        "title": "Go on a date with a girl from every US state",
        "completed": true
    },
    {
        "title": "Design and produce my own board/card game",
        "completed": true
    },
    {
        "title": "Take a photography class",
        "completed": true
    },
    {
        "title": "Go black water rafting",
        "completed": true
    },
    {
        "title": "Attend a country music concert",
        "completed": true
    },
    {
        "title": "Visit the Louvre",
        "completed": true
    },
    {
        "title": "Ride a cable car in San Francisco",
        "completed": true
    },
    {
        "title": "Attend Wrestlemania",
        "completed": true
    },
    {
        "title": "Bathe in natural hot springs",
        "completed": true
    },
    {
        "title": "Ride the Fremont Street zipline",
        "completed": true
    },
    {
        "title": "Walk the Milford Trek",
        "completed": true
    },
    {
        "title": "Hike through Jiuzhaigou",
        "completed": true
    },
    {
        "title": "Go stargazing",
        "completed": true
    },
    {
        "title": "Kiss passionately in the pouring rain",
        "completed": true
    },
    {
        "title": "Visit the Atacama Desert",
        "completed": true
    },
    {
        "title": "Explore the Ruins of Petra",
        "completed": true
    },
    {
        "title": "Fly a plane",
        "completed": true
    },
    {
        "title": "Cosplay at a convention",
        "completed": true
    },
    {
        "title": "Have a romantic weekend at a B&B",
        "completed": false
    },
    {
        "title": "Visit the San Diego Zoo",
        "completed": true
    },
    {
        "title": "Visit all of the ‘Stans",
        "completed": true
    },
    {
        "title": "Attend the Harbin Ice Festival",
        "completed": true
    },
    {
        "title": "Attend a Renaissance Festival",
        "completed": true
    },
    {
        "title": "Drink banana gin in Uganda",
        "completed": true
    },
    {
        "title": "Visit the White Cliffs of Dover",
        "completed": true
    },
    {
        "title": "Visit Angkor Wat",
        "completed": true
    },
    {
        "title": "Attend Oktoberfest",
        "completed": true
    },
    {
        "title": "Ride the Maiden of the Mists",
        "completed": true
    },
    {
        "title": "Explore a mirror maze",
        "completed": true
    },
    {
        "title": "Attend a boxing match",
        "completed": true
    },
    {
        "title": "Make the pilgrimage to Jerusalem",
        "completed": false
    },
    {
        "title": "Attend the NRL Grand Final",
        "completed": true
    },
    {
        "title": "Celebrate 420 in Amsterdam",
        "completed": true
    },
    {
        "title": "Celebrate 420 in Amsterdam",
        "completed": true
    },
    {
        "title": "Ride in a limo",
        "completed": true
    },
    {
        "title": "Gamble in Monaco",
        "completed": true
    },
    {
        "title": "Visit the Cave of the Crystals",
        "completed": true
    },
    {
        "title": "See a moose in the wild",
        "completed": true
    },
    {
        "title": "Do a keg-stand",
        "completed": true
    },
    {
        "title": "Find an gemstone and turn it into some kind of jewelry",
        "completed": true
    },
    {
        "title": "Meet real gypsies",
        "completed": true
    },
    {
        "title": "Eat Mexican food in Mexico",
        "completed": true
    },
    {
        "title": "Visit Meteor Crater,  Arizona",
        "completed": true
    },
    {
        "title": "Drink airag in Mongolia",
        "completed": true
    },
    {
        "title": "Attend the Highland Games",
        "completed": true
    },
    {
        "title": "Attend the Olympic Games",
        "completed": true
    },
    {
        "title": "Participate in a sceance",
        "completed": true
    },
    {
        "title": "Cruise the Yangtze River",
        "completed": true
    },
    {
        "title": "Teach English in another country",
        "completed": true
    },
    {
        "title": "Visit Yosemite",
        "completed": true
    },
    {
        "title": "Explore the Batu Caves",
        "completed": true
    },
    {
        "title": "Participate in a LARP experience",
        "completed": true
    },
    {
        "title": "Try sensory deprivation",
        "completed": true
    },
    {
        "title": "Trek through the Andes on a donkey",
        "completed": true
    },
    {
        "title": "Spend a weekend at a Buddhist retreat",
        "completed": true
    },
    {
        "title": "Have something I do go viral",
        "completed": true
    },
    {
        "title": "Drink Guinness in Ireland",
        "completed": true
    },
    {
        "title": "Scuba dive The Wall",
        "completed": true
    },
    {
        "title": "Tackle the Bourbon Trail",
        "completed": true
    },
    {
        "title": "Visit Lake Eyre",
        "completed": true
    },
    {
        "title": "Bike along the Rhine River",
        "completed": true
    },
    {
        "title": "Drive a lamborgini",
        "completed": true
    },
    {
        "title": "Eat a Cornish pasty in Cornwall",
        "completed": true
    },
    {
        "title": "Throw a grenade",
        "completed": true
    },
    {
        "title": "Visit Yosemite",
        "completed": true
    },
    {
        "title": "Sit on a jury",
        "completed": true
    },
    {
        "title": "Holiday on a house boat",
        "completed": true
    },
    {
        "title": "Visit the Atacama Desert",
        "completed": true
    },
    {
        "title": "Perform an obnoxious karaoke duet with a girlfriend",
        "completed": true
    },
    {
        "title": "Complete a Master’s Degree",
        "completed": true
    },
    {
        "title": "Live like a king in Dubai",
        "completed": true
    },
    {
        "title": "Cross the Oresund Bridge",
        "completed": true
    },
    {
        "title": "Attend a comedy festival",
        "completed": true
    },
    {
        "title": "Scuba dive the Big Blue Hole",
        "completed": true
    },
    {
        "title": "Climb Mount Koscuiozko",
        "completed": true
    },
    {
        "title": "Ask out a woman I’ve just met",
        "completed": true
    },
    {
        "title": "Attend a lucha wrestling show",
        "completed": true
    },
    {
        "title": "Scuba dive The Wall",
        "completed": true
    },
    {
        "title": "Complete the Overland Trek in Cradle Mountain National Park",
        "completed": true
    },
    {
        "title": "Perform live stand up",
        "completed": true
    },
    {
        "title": "Go whitewater rafting",
        "completed": true
    },
    {
        "title": "Attend the Australian Celtic Festival",
        "completed": true
    },
    {
        "title": "Go to the top of the Burj Khalifa",
        "completed": true
    },
    {
        "title": "Be in a live studio audience",
        "completed": true
    },
    {
        "title": "Get PADI Dive Master certified",
        "completed": true
    },
    {
        "title": "Ride on Puffing Billy",
        "completed": true
    },
    {
        "title": "See a show at the Opera House",
        "completed": true
    },
    {
        "title": "Be treated like a VIP in a club",
        "completed": true
    },
    {
        "title": "Ride a camel",
        "completed": true
    },
    {
        "title": "Ride in a limo",
        "completed": true
    },
    {
        "title": "Eat gumbo in Louisiana",
        "completed": true
    },
    {
        "title": "Explore the Mendenhall Caves",
        "completed": true
    },
    {
        "title": "Ride the ten tallest roller coasters on earth",
        "completed": true
    },
    {
        "title": "Visit Kronenberg Castle",
        "completed": true
    },
    {
        "title": "Kayak through the Grand Canyon",
        "completed": true
    },
    {
        "title": "Swim in the Hamilton Pool",
        "completed": false
    },
    {
        "title": "Attend La Tomatina",
        "completed": true
    },
    {
        "title": "Visit the Playa de las Catedrales",
        "completed": true
    },
    {
        "title": "Visit the Hagia Sophia",
        "completed": false
    },
    {
        "title": "Explore London",
        "completed": true
    },
    {
        "title": "Fly a stunt plane with U Fly Xtreme",
        "completed": true
    },
    {
        "title": "Scuba dive on every continent",
        "completed": true
    },
    {
        "title": "Become an uncle",
        "completed": true
    },
    {
        "title": "Fly First Class",
        "completed": true
    },
    {
        "title": "Stand beside Hadrian’s Wall",
        "completed": true
    },
    {
        "title": "Cross the intersection at Abbey Road",
        "completed": false
    },
    {
        "title": "Attend an AFL game",
        "completed": true
    },
    {
        "title": "Complete the Overland Trek in Cradle Mountain National Park",
        "completed": true
    },
    {
        "title": "Visit Kamchatkha Peninsula",
        "completed": true
    },
    {
        "title": "Walk or ride across the Golden Gate Bridge",
        "completed": true
    },
    {
        "title": "Spend Christmas in Lapland",
        "completed": true
    },
    {
        "title": "Attend a 7s or 9s tournament",
        "completed": true
    },
    {
        "title": "Attend a live NFL game",
        "completed": true
    },
    {
        "title": "Jump into a fountain fully clothed",
        "completed": true
    },
    {
        "title": "Visit Sol de Manana",
        "completed": true
    },
    {
        "title": "See Mount Roraima",
        "completed": true
    },
    {
        "title": "See a ghost",
        "completed": true
    },
    {
        "title": "Ride a segway",
        "completed": true
    },
    {
        "title": "Go to a techno club in Berlin",
        "completed": true
    },
    {
        "title": "Visit the San Diego Zoo",
        "completed": true
    },
    {
        "title": "Attend a TBEX event",
        "completed": true
    },
    {
        "title": "Visit Mount Fuji",
        "completed": true
    },
    {
        "title": "Throw a coin in Trevi Fountain",
        "completed": true
    },
    {
        "title": "Attend a comedy festival",
        "completed": true
    },
    {
        "title": "Fire a gun",
        "completed": true
    },
    {
        "title": "See the Terra Cotta Warriors",
        "completed": true
    },
    {
        "title": "Play Santa at a party",
        "completed": true
    },
    {
        "title": "Have a debauched boy’s weekend in a country other than my own",
        "completed": true
    },
    {
        "title": "Travel by helicopter",
        "completed": true
    },
    {
        "title": "Visit Ngorogoro Crater",
        "completed": true
    },
    {
        "title": "Pose for a life drawing class",
        "completed": false
    },
    {
        "title": "Drink elephant dung coffee in Cambodia",
        "completed": true
    },
    {
        "title": "Go rock climbing outside of a gym",
        "completed": true
    },
    {
        "title": "Quit a job in a dramatic way",
        "completed": true
    },
    {
        "title": "Chop my own firewood",
        "completed": true
    },
    {
        "title": "Get a professional massage",
        "completed": true
    },
    {
        "title": "See the 12 Apostles and the Great Ocean Road",
        "completed": true
    },
    {
        "title": "See a show at the Opera House",
        "completed": true
    },
    {
        "title": "Search for the Loch Ness Monster",
        "completed": true
    },
    {
        "title": "Drift dive",
        "completed": true
    },
    {
        "title": "Win a championship with a team",
        "completed": true
    },
    {
        "title": "See a geyser erupt",
        "completed": true
    },
    {
        "title": "Have an article published in a newspaper or magazine",
        "completed": true
    },
    {
        "title": "See a great white shark in the wild",
        "completed": true
    },
    {
        "title": "Drink elephant dung coffee in Cambodia",
        "completed": false
    },
    {
        "title": "See a ghost",
        "completed": true
    },
    {
        "title": "Visit Singapore",
        "completed": true
    },
    {
        "title": "Have a beer with one of my heroes",
        "completed": true
    },
    {
        "title": "Eat gumbo in Louisiana",
        "completed": true
    },
    {
        "title": "Visit Jejudo",
        "completed": true
    },
    {
        "title": "Visit all five of China’s Sacred Mountains",
        "completed": false
    },
    {
        "title": "Become fluent in another language",
        "completed": true
    },
    {
        "title": "Ride the Ghan or the Indian Pacific",
        "completed": true
    },
    {
        "title": "See a UFO",
        "completed": true
    },
    {
        "title": "Visit Westminster Abbey",
        "completed": true
    },
    {
        "title": "Ride the Maiden of the Mists",
        "completed": true
    },
    {
        "title": "Paratroop",
        "completed": true
    },
    {
        "title": "Attend Mardi Gras in New Orleans",
        "completed": true
    },
    {
        "title": "Visit the Blue Lagoon in Iceland",
        "completed": true
    },
    {
        "title": "Visit Yellowstone",
        "completed": true
    },
    {
        "title": "Paratroop",
        "completed": true
    },
    {
        "title": "Drink milk straight from a coconut",
        "completed": true
    },
    {
        "title": "Attend an F1 event",
        "completed": true
    },
    {
        "title": "Ring in New Year’s with a kiss",
        "completed": true
    },
    {
        "title": "Attend a wrestling PPV",
        "completed": true
    },
    {
        "title": "Attend the Henley-on-Todd Regata",
        "completed": true
    },
    {
        "title": "Attend a music festival",
        "completed": true
    },
    {
        "title": "Go Guerilla Camping",
        "completed": true
    },
    {
        "title": "Visit Capitol Hill",
        "completed": true
    },
    {
        "title": "See Mount Roraima",
        "completed": true
    },
    {
        "title": "Drift dive",
        "completed": true
    },
    {
        "title": "Visit the Wizarding World of Harry Potter",
        "completed": true
    },
    {
        "title": "Go zorbing",
        "completed": true
    },
    {
        "title": "Explore the Olympic National park",
        "completed": true
    },
    {
        "title": "Attend the Sydney Gay & Lesbian Mardi Gras",
        "completed": true
    },
    {
        "title": "Visit Siberia",
        "completed": true
    },
    {
        "title": "Visit Bora Bora",
        "completed": true
    },
    {
        "title": "Serenade somebody",
        "completed": true
    },
    {
        "title": "Sell a photo/Get paid to take photos",
        "completed": true
    },
    {
        "title": "Run an obstacle course",
        "completed": true
    },
    {
        "title": "Drink banana gin in Uganda",
        "completed": true
    },
    {
        "title": "Drink kava in Fiji",
        "completed": true
    },
    {
        "title": "Visit Lake Eyre",
        "completed": true
    },
    {
        "title": "Become an uncle",
        "completed": true
    },
    {
        "title": "Drink Guinness in Ireland",
        "completed": true
    },
    {
        "title": "Attend El Classico",
        "completed": true
    },
    {
        "title": "Pose for a sexy calendar for charity",
        "completed": true
    },
    {
        "title": "Visit Singapore",
        "completed": true
    },
    {
        "title": "Visit the Hagia Sophia",
        "completed": true
    },
    {
        "title": "Go rock climbing outside of a gym",
        "completed": true
    }
]